hyperparse/__init__.py
hyperparse/hyperparse.py
hyperparse/version.py
hyperparse-0.0.8.dist-info/METADATA
hyperparse-0.0.8.dist-info/WHEEL
hyperparse-0.0.8.dist-info/top_level.txt
hyperparse-0.0.8.dist-info/RECORD
