Metadata-Version: 2.4
Name: hyperparse
Version: 0.0.8
Summary: Parse shell env variables to python dict
Home-page: https://github.com/fuzihaofzh/hyperparse
Author: 
Author-email: 
Keywords: Shell env
Classifier: Programming Language :: Python :: 3.7
Dynamic: classifier
Dynamic: description
Dynamic: description-content-type
Dynamic: home-page
Dynamic: keywords
Dynamic: summary
